supplier_evaluator/__init__.py
supplier_evaluator/evaluate_tool.py
supplier_evaluator-0.1.0.dist-info/METADATA
supplier_evaluator-0.1.0.dist-info/WHEEL
supplier_evaluator-0.1.0.dist-info/top_level.txt
supplier_evaluator-0.1.0.dist-info/RECORD
