Metadata-Version: 2.4
Name: supplier_evaluator
Version: 0.1.0
Summary: Tool to evaluate supplier quotations based on price, delivery date, and quality.
Author: Your Name
Requires-Python: >=3.7
Requires-Dist: pandas
Requires-Dist: numpy
Requires-Dist: pydantic
Requires-Dist: crewai
Dynamic: author
Dynamic: requires-dist
Dynamic: requires-python
Dynamic: summary
